MANIFEST.in
README.txt
setup.cfg
setup.py
docs/HISTORY.txt
src/collective/__init__.py
src/collective.elasticindex.egg-info/PKG-INFO
src/collective.elasticindex.egg-info/SOURCES.txt
src/collective.elasticindex.egg-info/dependency_links.txt
src/collective.elasticindex.egg-info/namespace_packages.txt
src/collective.elasticindex.egg-info/not-zip-safe
src/collective.elasticindex.egg-info/requires.txt
src/collective.elasticindex.egg-info/top_level.txt
src/collective/elasticindex/__init__.py
src/collective/elasticindex/changes.py
src/collective/elasticindex/configure.zcml
src/collective/elasticindex/interfaces.py
src/collective/elasticindex/settings.py
src/collective/elasticindex/subscribers.py
src/collective/elasticindex/utils.py
src/collective/elasticindex/browser/__init__.py
src/collective/elasticindex/browser/configure.zcml
src/collective/elasticindex/browser/loading.gif
src/collective/elasticindex/browser/portlet.pt
src/collective/elasticindex/browser/portlet.py
src/collective/elasticindex/browser/search.css
src/collective/elasticindex/browser/search.js
src/collective/elasticindex/browser/search.pt
src/collective/elasticindex/browser/search.py
src/collective/elasticindex/browser/settings.py
src/collective/elasticindex/profiles/default/controlpanel.xml
src/collective/elasticindex/profiles/default/portlets.xml
src/collective/elasticindex/profiles/default/propertiestool.xml
src/collective/elasticindex/tests/__init__.py
src/collective/elasticindex/tests/base.py
src/collective/elasticindex/tests/test_indexing.py