Metadata-Version: 1.1
Name: collective.elasticindex
Version: 1.2.2
Summary: Index Plone content in Elastic Search
Home-page: https://github.com/infrae/collective.elasticindex
Author: Infrae
Author-email: info@infrae.com
License: BSD
Keywords: plone index elasticsearch search
Platform: UNKNOWN
Classifier: Programming Language :: Python
